met_brewer
