Metadata-Version: 2.1
Name: met-brewer
Version: 1.0.2
